README.md
esl_redis.py
setup.py
esl_redis.egg-info/PKG-INFO
esl_redis.egg-info/SOURCES.txt
esl_redis.egg-info/dependency_links.txt
esl_redis.egg-info/entry_points.txt
esl_redis.egg-info/requires.txt
esl_redis.egg-info/top_level.txt